{
  "time": 1627207371845,
  "version": {
    "sideex": [
      3,
      5,
      3
    ],
    "format": [
      2,
      0,
      0
    ]
  },
  "suites": [
    {
      "title": "Untitled Test Suite",
      "enableOnPlaying": true,
      "cases": [
        {
          "title": "verifyTitle",
          "enableOnPlaying": true,
          "networkSpeed": 28.89,
          "records": [
            {
              "name": "open",
              "target": {
                "usedIndex": 0,
                "options": [
                  {
                    "type": "other",
                    "value": "https://sideex.github.io/example/webpage_under_test/search-box.html"
                  }
                ],
                "tac": ""
              },
              "value": {
                "usedIndex": 0,
                "options": [
                  {
                    "type": "other",
                    "value": ""
                  }
                ],
                "tac": ""
              },
              "pwt": {
                "pbw": 0,
                "paw": 0,
                "prw": 0,
                "pdw": 0
              },
              "comment": false
            },
            {
              "name": "setViewportSize",
              "target": {
                "usedIndex": 0,
                "options": [
                  {
                    "type": "other",
                    "value": ""
                  }
                ],
                "tac": ""
              },
              "value": {
                "usedIndex": 0,
                "options": [
                  {
                    "type": "other",
                    "value": "1440,692"
                  }
                ],
                "tac": ""
              },
              "pwt": {
                "pbw": 0,
                "paw": 0,
                "prw": 0,
                "pdw": 0
              },
              "comment": false
            },
            {
              "name": "verifyTitle",
              "target": {
                "usedIndex": 0,
                "options": [
                  {
                    "type": "other",
                    "value": "search-box"
                  }
                ],
                "tac": ""
              },
              "value": {
                "usedIndex": 0,
                "options": [
                  {
                    "type": "other",
                    "value": ""
                  }
                ],
                "tac": ""
              },
              "pwt": {
                "pbw": 0,
                "paw": 0,
                "prw": 0,
                "pdw": 0
              },
              "comment": false
            }
          ]
        }
      ]
    }
  ]
}